rangefilter/__init__.py
rangefilter/apps.py
rangefilter/filter.py
rangefilter/filters.py
rangefilter/models.py
rangefilter/settings.py
rangefilter/locale/cs_CZ/LC_MESSAGES/django.mo
rangefilter/locale/cs_CZ/LC_MESSAGES/django.po
rangefilter/locale/da/LC_MESSAGES/django.mo
rangefilter/locale/da/LC_MESSAGES/django.po
rangefilter/locale/de/LC_MESSAGES/django.mo
rangefilter/locale/de/LC_MESSAGES/django.po
rangefilter/locale/el/LC_MESSAGES/django.mo
rangefilter/locale/el/LC_MESSAGES/django.po
rangefilter/locale/en_US/LC_MESSAGES/django.mo
rangefilter/locale/en_US/LC_MESSAGES/django.po
rangefilter/locale/es/LC_MESSAGES/django.mo
rangefilter/locale/es/LC_MESSAGES/django.po
rangefilter/locale/es_AR/LC_MESSAGES/django.mo
rangefilter/locale/es_AR/LC_MESSAGES/django.po
rangefilter/locale/fa/LC_MESSAGES/django.mo
rangefilter/locale/fa/LC_MESSAGES/django.po
rangefilter/locale/fr/LC_MESSAGES/django.mo
rangefilter/locale/fr/LC_MESSAGES/django.po
rangefilter/locale/it/LC_MESSAGES/django.mo
rangefilter/locale/it/LC_MESSAGES/django.po
rangefilter/locale/ja/LC_MESSAGES/django.mo
rangefilter/locale/ja/LC_MESSAGES/django.po
rangefilter/locale/pl/LC_MESSAGES/django.mo
rangefilter/locale/pl/LC_MESSAGES/django.po
rangefilter/locale/pt_BR/LC_MESSAGES/django.mo
rangefilter/locale/pt_BR/LC_MESSAGES/django.po
rangefilter/locale/pt_PT/LC_MESSAGES/django.mo
rangefilter/locale/pt_PT/LC_MESSAGES/django.po
rangefilter/locale/ru/LC_MESSAGES/django.mo
rangefilter/locale/ru/LC_MESSAGES/django.po
rangefilter/locale/uk/LC_MESSAGES/django.mo
rangefilter/locale/uk/LC_MESSAGES/django.po
rangefilter/locale/zh_CN/LC_MESSAGES/django.mo
rangefilter/locale/zh_CN/LC_MESSAGES/django.po
rangefilter/locale/zh_Hans/LC_MESSAGES/django.mo
rangefilter/locale/zh_Hans/LC_MESSAGES/django.po
rangefilter/static/rangefilter/iife.js
rangefilter/templates/rangefilter/date_filter.html
rangefilter/templates/rangefilter/date_filter_1_8.html
rangefilter/templates/rangefilter/date_filter_csp.html
django_jazzmin_admin_rangefilter-1.0.0.dist-info/LICENSE
django_jazzmin_admin_rangefilter-1.0.0.dist-info/METADATA
django_jazzmin_admin_rangefilter-1.0.0.dist-info/WHEEL
django_jazzmin_admin_rangefilter-1.0.0.dist-info/top_level.txt
django_jazzmin_admin_rangefilter-1.0.0.dist-info/RECORD
